Compiled from "TransformerRuntime.java"
public class dev.architectury.transformer.TransformerRuntime {
  public static final java.lang.String RUNTIME_TRANSFORM_CONFIG;

  public static final java.lang.String MAIN_CLASS;

  public static final java.lang.String PROPERTIES;

  public static final java.util.Set<java.io.File> TRANSFORM_FILES;

  public static final java.util.Map<java.lang.String, dev.architectury.transformer.TransformerRuntime$ToTransformData> CLASSES_TO_TRANSFORM;

  private static dev.architectury.transformer.transformers.classpath.ReadClasspathProvider classpathProvider;

  public dev.architectury.transformer.TransformerRuntime();
    Code:
         0: aload_0
         1: invokespecial #1                  // Method java/lang/Object."<init>":()V
         4: return

  private static boolean isDebugOutputEnabled();
    Code:
         0: ldc           #3                  // String architectury.transformer.debug_output
         2: ldc           #4                  // String false
         4: invokestatic  #5                  // Method java/lang/System.getProperty:(Ljava/lang/String;Ljava/lang/String;)Ljava/lang/String;
         7: ldc           #6                  // String true
         9: invokevirtual #7                  // Method java/lang/String.equals:(Ljava/lang/Object;)Z
        12: ireturn

  public static void main(java.lang.String[]) throws java.lang.Throwable;
    Code:
         0: new           #8                  // class java/lang/StringBuilder
         3: dup
         4: invokespecial #9                  // Method java/lang/StringBuilder."<init>":()V
         7: ldc           #10                 // String Architectury Runtime
         9: invokevirtual #11                 // Method java/lang/StringBuilder.append:(Ljava/lang/String;)Ljava/lang/StringBuilder;
        12: ldc           #12                 // class dev/architectury/transformer/TransformerRuntime
        14: invokevirtual #13                 // Method java/lang/Class.getPackage:()Ljava/lang/Package;
        17: invokevirtual #14                 // Method java/lang/Package.getImplementationVersion:()Ljava/lang/String;
        20: invokevirtual #11                 // Method java/lang/StringBuilder.append:(Ljava/lang/String;)Ljava/lang/StringBuilder;
        23: invokevirtual #15                 // Method java/lang/StringBuilder.toString:()Ljava/lang/String;
        26: invokestatic  #16                 // Method dev/architectury/transformer/util/Logger.info:(Ljava/lang/String;)V
        29: new           #17                 // class java/util/ArrayList
        32: dup
        33: aload_0
        34: invokestatic  #18                 // Method java/util/Arrays.asList:([Ljava/lang/Object;)Ljava/util/List;
        37: invokespecial #19                 // Method java/util/ArrayList."<init>":(Ljava/util/Collection;)V
        40: astore_1
        41: invokestatic  #20                 // Method applyProperties:()V
        44: ldc           #21                 // String architectury.runtime.transformer
        46: invokestatic  #22                 // Method java/lang/System.getProperty:(Ljava/lang/String;)Ljava/lang/String;
        49: iconst_0
        50: anewarray     #23                 // class java/lang/String
        53: invokestatic  #24                 // Method java/nio/file/Paths.get:(Ljava/lang/String;[Ljava/lang/String;)Ljava/nio/file/Path;
        56: astore_2
        57: new           #23                 // class java/lang/String
        60: dup
        61: aload_2
        62: invokestatic  #25                 // Method java/nio/file/Files.readAllBytes:(Ljava/nio/file/Path;)[B
        65: getstatic     #26                 // Field java/nio/charset/StandardCharsets.UTF_8:Ljava/nio/charset/Charset;
        68: invokespecial #27                 // Method java/lang/String."<init>":([BLjava/nio/charset/Charset;)V
        71: astore_3
        72: aload_3
        73: invokestatic  #28                 // Method parsePathWithTransformersEntries:(Ljava/lang/String;)Ljava/util/List;
        76: astore        4
        78: new           #29                 // class java/util/concurrent/atomic/AtomicInteger
        81: dup
        82: invokespecial #30                 // Method java/util/concurrent/atomic/AtomicInteger."<init>":()V
        85: astore        5
        87: new           #31                 // class java/util/concurrent/ConcurrentHashMap
        90: dup
        91: invokespecial #32                 // Method java/util/concurrent/ConcurrentHashMap."<init>":()V
        94: astore        6
        96: aload         4
        98: invokeinterface #33,  1           // InterfaceMethod java/util/List.iterator:()Ljava/util/Iterator;
       103: astore        7
       105: aload         7
       107: invokeinterface #34,  1           // InterfaceMethod java/util/Iterator.hasNext:()Z
       112: ifeq          447
       115: aload         7
       117: invokeinterface #35,  1           // InterfaceMethod java/util/Iterator.next:()Ljava/lang/Object;
       122: checkcast     #36                 // class dev/architectury/transformer/TransformerRuntime$PathWithTransformersEntry
       125: astore        8
       127: invokestatic  #37                 // Method isDebugOutputEnabled:()Z
       130: ifeq          160
       133: aload         6
       135: aload         8
       137: invokevirtual #38                 // Method dev/architectury/transformer/TransformerRuntime$PathWithTransformersEntry.getPath:()Ljava/nio/file/Path;
       140: aload         8
       142: aload         5
       144: invokedynamic #39,  0             // InvokeDynamic #0:apply:(Ldev/architectury/transformer/TransformerRuntime$PathWithTransformersEntry;Ljava/util/concurrent/atomic/AtomicInteger;)Ljava/util/function/Function;
       149: invokeinterface #40,  3           // InterfaceMethod java/util/Map.computeIfAbsent:(Ljava/lang/Object;Ljava/util/function/Function;)Ljava/lang/Object;
       154: checkcast     #41                 // class dev/architectury/transformer/input/DirectoryFileAccess
       157: goto          161
       160: aconst_null
       161: astore        9
       163: getstatic     #42                 // Field TRANSFORM_FILES:Ljava/util/Set;
       166: aload         8
       168: invokevirtual #43                 // Method dev/architectury/transformer/TransformerRuntime$PathWithTransformersEntry.toFile:()Ljava/io/File;
       171: invokevirtual #44                 // Method java/io/File.getAbsoluteFile:()Ljava/io/File;
       174: invokeinterface #45,  2           // InterfaceMethod java/util/Set.add:(Ljava/lang/Object;)Z
       179: pop
       180: aload         8
       182: invokevirtual #38                 // Method dev/architectury/transformer/TransformerRuntime$PathWithTransformersEntry.getPath:()Ljava/nio/file/Path;
       185: iconst_0
       186: anewarray     #46                 // class java/nio/file/LinkOption
       189: invokestatic  #47                 // Method java/nio/file/Files.isDirectory:(Ljava/nio/file/Path;[Ljava/nio/file/LinkOption;)Z
       192: ifeq          321
       195: aload         8
       197: invokevirtual #38                 // Method dev/architectury/transformer/TransformerRuntime$PathWithTransformersEntry.getPath:()Ljava/nio/file/Path;
       200: invokestatic  #48                 // Method dev/architectury/transformer/input/OpenedFileAccess.ofDirectory:(Ljava/nio/file/Path;)Ldev/architectury/transformer/input/OpenedFileAccess;
       203: astore        10
       205: aconst_null
       206: astore        11
       208: aload         10
       210: invokevirtual #49                 // Method dev/architectury/transformer/input/OpenedFileAccess.remember:()Ldev/architectury/transformer/input/MemoryFileAccess;
       213: astore        12
       215: aload         10
       217: aload         8
       219: aload         12
       221: aload         9
       223: invokedynamic #50,  0             // InvokeDynamic #1:accept:(Ldev/architectury/transformer/TransformerRuntime$PathWithTransformersEntry;Ldev/architectury/transformer/input/MemoryFileAccess;Ldev/architectury/transformer/input/DirectoryFileAccess;)Ljava/util/function/Consumer;
       228: invokevirtual #51                 // Method dev/architectury/transformer/input/OpenedFileAccess.handle:(Ljava/util/function/Consumer;)V
       231: aload         10
       233: ifnull        318
       236: aload         11
       238: ifnull        261
       241: aload         10
       243: invokevirtual #52                 // Method dev/architectury/transformer/input/OpenedFileAccess.close:()V
       246: goto          318
       249: astore        12
       251: aload         11
       253: aload         12
       255: invokevirtual #54                 // Method java/lang/Throwable.addSuppressed:(Ljava/lang/Throwable;)V
       258: goto          318
       261: aload         10
       263: invokevirtual #52                 // Method dev/architectury/transformer/input/OpenedFileAccess.close:()V
       266: goto          318
       269: astore        12
       271: aload         12
       273: astore        11
       275: aload         12
       277: athrow
       278: astore        13
       280: aload         10
       282: ifnull        315
       285: aload         11
       287: ifnull        310
       290: aload         10
       292: invokevirtual #52                 // Method dev/architectury/transformer/input/OpenedFileAccess.close:()V
       295: goto          315
       298: astore        14
       300: aload         11
       302: aload         14
       304: invokevirtual #54                 // Method java/lang/Throwable.addSuppressed:(Ljava/lang/Throwable;)V
       307: goto          315
       310: aload         10
       312: invokevirtual #52                 // Method dev/architectury/transformer/input/OpenedFileAccess.close:()V
       315: aload         13
       317: athrow
       318: goto          444
       321: aload         8
       323: invokevirtual #38                 // Method dev/architectury/transformer/TransformerRuntime$PathWithTransformersEntry.getPath:()Ljava/nio/file/Path;
       326: invokestatic  #55                 // Method dev/architectury/transformer/input/OpenedFileAccess.ofJar:(Ljava/nio/file/Path;)Ldev/architectury/transformer/input/OpenedFileAccess;
       329: astore        10
       331: aconst_null
       332: astore        11
       334: aload         10
       336: invokevirtual #49                 // Method dev/architectury/transformer/input/OpenedFileAccess.remember:()Ldev/architectury/transformer/input/MemoryFileAccess;
       339: astore        12
       341: aload         10
       343: aload         8
       345: aload         12
       347: aload         9
       349: invokedynamic #56,  0             // InvokeDynamic #2:accept:(Ldev/architectury/transformer/TransformerRuntime$PathWithTransformersEntry;Ldev/architectury/transformer/input/MemoryFileAccess;Ldev/architectury/transformer/input/DirectoryFileAccess;)Ljava/util/function/Consumer;
       354: invokevirtual #51                 // Method dev/architectury/transformer/input/OpenedFileAccess.handle:(Ljava/util/function/Consumer;)V
       357: aload         10
       359: ifnull        444
       362: aload         11
       364: ifnull        387
       367: aload         10
       369: invokevirtual #52                 // Method dev/architectury/transformer/input/OpenedFileAccess.close:()V
       372: goto          444
       375: astore        12
       377: aload         11
       379: aload         12
       381: invokevirtual #54                 // Method java/lang/Throwable.addSuppressed:(Ljava/lang/Throwable;)V
       384: goto          444
       387: aload         10
       389: invokevirtual #52                 // Method dev/architectury/transformer/input/OpenedFileAccess.close:()V
       392: goto          444
       395: astore        12
       397: aload         12
       399: astore        11
       401: aload         12
       403: athrow
       404: astore        15
       406: aload         10
       408: ifnull        441
       411: aload         11
       413: ifnull        436
       416: aload         10
       418: invokevirtual #52                 // Method dev/architectury/transformer/input/OpenedFileAccess.close:()V
       421: goto          441
       424: astore        16
       426: aload         11
       428: aload         16
       430: invokevirtual #54                 // Method java/lang/Throwable.addSuppressed:(Ljava/lang/Throwable;)V
       433: goto          441
       436: aload         10
       438: invokevirtual #52                 // Method dev/architectury/transformer/input/OpenedFileAccess.close:()V
       441: aload         15
       443: athrow
       444: goto          105
       447: new           #17                 // class java/util/ArrayList
       450: dup
       451: invokespecial #57                 // Method java/util/ArrayList."<init>":()V
       454: astore        7
       456: invokestatic  #58                 // InterfaceMethod dev/architectury/transformer/transformers/ClasspathProvider.fromProperties:()Ldev/architectury/transformer/transformers/ClasspathProvider;
       459: aload         4
       461: invokedynamic #59,  0             // InvokeDynamic #3:test:(Ljava/util/List;)Ljava/util/function/Predicate;
       466: invokeinterface #60,  2           // InterfaceMethod dev/architectury/transformer/transformers/ClasspathProvider.filter:(Ljava/util/function/Predicate;)Ldev/architectury/transformer/transformers/ClasspathProvider;
       471: invokestatic  #61                 // InterfaceMethod dev/architectury/transformer/transformers/classpath/ReadClasspathProvider.of:(Ldev/architectury/transformer/transformers/ClasspathProvider;)Ldev/architectury/transformer/transformers/classpath/ReadClasspathProvider;
       474: putstatic     #62                 // Field classpathProvider:Ldev/architectury/transformer/transformers/classpath/ReadClasspathProvider;
       477: invokestatic  #63                 // Method doInstrumentationStuff:()V
       480: aload         4
       482: invokeinterface #33,  1           // InterfaceMethod java/util/List.iterator:()Ljava/util/Iterator;
       487: astore        8
       489: aload         8
       491: invokeinterface #34,  1           // InterfaceMethod java/util/Iterator.hasNext:()Z
       496: ifeq          1012
       499: aload         8
       501: invokeinterface #35,  1           // InterfaceMethod java/util/Iterator.next:()Ljava/lang/Object;
       506: checkcast     #36                 // class dev/architectury/transformer/TransformerRuntime$PathWithTransformersEntry
       509: astore        9
       511: new           #64                 // class java/util/HashMap
       514: dup
       515: invokespecial #65                 // Method java/util/HashMap."<init>":()V
       518: astore        10
       520: aload         6
       522: aload         9
       524: invokevirtual #38                 // Method dev/architectury/transformer/TransformerRuntime$PathWithTransformersEntry.getPath:()Ljava/nio/file/Path;
       527: invokeinterface #66,  2           // InterfaceMethod java/util/Map.get:(Ljava/lang/Object;)Ljava/lang/Object;
       532: checkcast     #41                 // class dev/architectury/transformer/input/DirectoryFileAccess
       535: astore        11
       537: aconst_null
       538: ldc           #67                 // String .jar
       540: iconst_0
       541: anewarray     #68                 // class java/nio/file/attribute/FileAttribute
       544: invokestatic  #69                 // Method java/nio/file/Files.createTempFile:(Ljava/lang/String;Ljava/lang/String;[Ljava/nio/file/attribute/FileAttribute;)Ljava/nio/file/Path;
       547: astore        12
       549: aload         7
       551: new           #70                 // class java/util/AbstractMap$SimpleEntry
       554: dup
       555: aload         12
       557: aload         9
       559: invokespecial #71                 // Method java/util/AbstractMap$SimpleEntry."<init>":(Ljava/lang/Object;Ljava/lang/Object;)V
       562: invokeinterface #72,  2           // InterfaceMethod java/util/List.add:(Ljava/lang/Object;)Z
       567: pop
       568: aload         12
       570: invokestatic  #73                 // Method java/nio/file/Files.deleteIfExists:(Ljava/nio/file/Path;)Z
       573: pop
       574: aload         12
       576: invokestatic  #55                 // Method dev/architectury/transformer/input/OpenedFileAccess.ofJar:(Ljava/nio/file/Path;)Ldev/architectury/transformer/input/OpenedFileAccess;
       579: astore        13
       581: aconst_null
       582: astore        14
       584: aload         9
       586: invokevirtual #38                 // Method dev/architectury/transformer/TransformerRuntime$PathWithTransformersEntry.getPath:()Ljava/nio/file/Path;
       589: invokestatic  #55                 // Method dev/architectury/transformer/input/OpenedFileAccess.ofJar:(Ljava/nio/file/Path;)Ldev/architectury/transformer/input/OpenedFileAccess;
       592: astore        15
       594: aconst_null
       595: astore        16
       597: aload         15
       599: aload         13
       601: invokevirtual #74                 // Method dev/architectury/transformer/input/OpenedFileAccess.copyTo:(Ldev/architectury/transformer/input/FileAccess;)V
       604: aload         15
       606: ifnull        691
       609: aload         16
       611: ifnull        634
       614: aload         15
       616: invokevirtual #52                 // Method dev/architectury/transformer/input/OpenedFileAccess.close:()V
       619: goto          691
       622: astore        17
       624: aload         16
       626: aload         17
       628: invokevirtual #54                 // Method java/lang/Throwable.addSuppressed:(Ljava/lang/Throwable;)V
       631: goto          691
       634: aload         15
       636: invokevirtual #52                 // Method dev/architectury/transformer/input/OpenedFileAccess.close:()V
       639: goto          691
       642: astore        17
       644: aload         17
       646: astore        16
       648: aload         17
       650: athrow
       651: astore        18
       653: aload         15
       655: ifnull        688
       658: aload         16
       660: ifnull        683
       663: aload         15
       665: invokevirtual #52                 // Method dev/architectury/transformer/input/OpenedFileAccess.close:()V
       668: goto          688
       671: astore        19
       673: aload         16
       675: aload         19
       677: invokevirtual #54                 // Method java/lang/Throwable.addSuppressed:(Ljava/lang/Throwable;)V
       680: goto          688
       683: aload         15
       685: invokevirtual #52                 // Method dev/architectury/transformer/input/OpenedFileAccess.close:()V
       688: aload         18
       690: athrow
       691: new           #8                  // class java/lang/StringBuilder
       694: dup
       695: invokespecial #9                  // Method java/lang/StringBuilder."<init>":()V
       698: ldc           #75                 // String Transforming
       700: invokevirtual #11                 // Method java/lang/StringBuilder.append:(Ljava/lang/String;)Ljava/lang/StringBuilder;
       703: aload         9
       705: invokevirtual #76                 // Method dev/architectury/transformer/TransformerRuntime$PathWithTransformersEntry.getTransformers:()Ljava/util/List;
       708: invokeinterface #77,  1           // InterfaceMethod java/util/List.size:()I
       713: invokevirtual #78                 // Method java/lang/StringBuilder.append:(I)Ljava/lang/StringBuilder;
       716: ldc           #79                 // String  transformer(s) from
       718: invokevirtual #11                 // Method java/lang/StringBuilder.append:(Ljava/lang/String;)Ljava/lang/StringBuilder;
       721: aload         9
       723: invokevirtual #38                 // Method dev/architectury/transformer/TransformerRuntime$PathWithTransformersEntry.getPath:()Ljava/nio/file/Path;
       726: invokeinterface #80,  1           // InterfaceMethod java/nio/file/Path.toString:()Ljava/lang/String;
       731: invokevirtual #11                 // Method java/lang/StringBuilder.append:(Ljava/lang/String;)Ljava/lang/StringBuilder;
       734: ldc           #81                 // String  to
       736: invokevirtual #11                 // Method java/lang/StringBuilder.append:(Ljava/lang/String;)Ljava/lang/StringBuilder;
       739: aload         12
       741: invokevirtual #82                 // Method java/lang/StringBuilder.append:(Ljava/lang/Object;)Ljava/lang/StringBuilder;
       744: ldc           #83                 // String :
       746: invokevirtual #11                 // Method java/lang/StringBuilder.append:(Ljava/lang/String;)Ljava/lang/StringBuilder;
       749: invokevirtual #15                 // Method java/lang/StringBuilder.toString:()Ljava/lang/String;
       752: invokestatic  #84                 // Method dev/architectury/transformer/util/Logger.debug:(Ljava/lang/String;)V
       755: aload         9
       757: invokevirtual #76                 // Method dev/architectury/transformer/TransformerRuntime$PathWithTransformersEntry.getTransformers:()Ljava/util/List;
       760: invokeinterface #33,  1           // InterfaceMethod java/util/List.iterator:()Ljava/util/Iterator;
       765: astore        15
       767: aload         15
       769: invokeinterface #34,  1           // InterfaceMethod java/util/Iterator.hasNext:()Z
       774: ifeq          818
       777: aload         15
       779: invokeinterface #35,  1           // InterfaceMethod java/util/Iterator.next:()Ljava/lang/Object;
       784: checkcast     #85                 // class dev/architectury/transformer/Transformer
       787: astore        16
       789: new           #8                  // class java/lang/StringBuilder
       792: dup
       793: invokespecial #9                  // Method java/lang/StringBuilder."<init>":()V
       796: ldc           #86                 // String  -
       798: invokevirtual #11                 // Method java/lang/StringBuilder.append:(Ljava/lang/String;)Ljava/lang/StringBuilder;
       801: aload         16
       803: invokevirtual #87                 // Method java/lang/Object.toString:()Ljava/lang/String;
       806: invokevirtual #11                 // Method java/lang/StringBuilder.append:(Ljava/lang/String;)Ljava/lang/StringBuilder;
       809: invokevirtual #15                 // Method java/lang/StringBuilder.toString:()Ljava/lang/String;
       812: invokestatic  #84                 // Method dev/architectury/transformer/util/Logger.debug:(Ljava/lang/String;)V
       815: goto          767
       818: new           #88                 // class dev/architectury/transformer/transformers/base/edit/SimpleTransformerContext
       821: dup
       822: aload_1
       823: invokedynamic #89,  0             // InvokeDynamic #4:accept:(Ljava/util/List;)Ljava/util/function/Consumer;
       828: iconst_0
       829: iconst_1
       830: iconst_1
       831: invokespecial #90                 // Method dev/architectury/transformer/transformers/base/edit/SimpleTransformerContext."<init>":(Ljava/util/function/Consumer;ZZZ)V
       834: getstatic     #62                 // Field classpathProvider:Ldev/architectury/transformer/transformers/classpath/ReadClasspathProvider;
       837: aload         9
       839: invokevirtual #38                 // Method dev/architectury/transformer/TransformerRuntime$PathWithTransformersEntry.getPath:()Ljava/nio/file/Path;
       842: invokeinterface #80,  1           // InterfaceMethod java/nio/file/Path.toString:()Ljava/lang/String;
       847: new           #91                 // class dev/architectury/transformer/RuntimeFileAccess
       850: dup
       851: aload         10
       853: aload         13
       855: aload         11
       857: invokespecial #92                 // Method dev/architectury/transformer/RuntimeFileAccess."<init>":(Ljava/util/Map;Ldev/architectury/transformer/input/FileAccess;Ldev/architectury/transformer/input/FileAccess;)V
       860: aload         9
       862: invokevirtual #76                 // Method dev/architectury/transformer/TransformerRuntime$PathWithTransformersEntry.getTransformers:()Ljava/util/List;
       865: invokestatic  #93                 // Method dev/architectury/transformer/Transform.runTransformers:(Ldev/architectury/transformer/transformers/base/edit/TransformerContext;Ldev/architectury/transformer/transformers/classpath/ReadClasspathProvider;Ljava/lang/String;Ldev/architectury/transformer/input/FileAccess;Ljava/util/List;)V
       868: aload         13
       870: ifnull        955
       873: aload         14
       875: ifnull        898
       878: aload         13
       880: invokevirtual #52                 // Method dev/architectury/transformer/input/OpenedFileAccess.close:()V
       883: goto          955
       886: astore        15
       888: aload         14
       890: aload         15
       892: invokevirtual #54                 // Method java/lang/Throwable.addSuppressed:(Ljava/lang/Throwable;)V
       895: goto          955
       898: aload         13
       900: invokevirtual #52                 // Method dev/architectury/transformer/input/OpenedFileAccess.close:()V
       903: goto          955
       906: astore        15
       908: aload         15
       910: astore        14
       912: aload         15
       914: athrow
       915: astore        20
       917: aload         13
       919: ifnull        952
       922: aload         14
       924: ifnull        947
       927: aload         13
       929: invokevirtual #52                 // Method dev/architectury/transformer/input/OpenedFileAccess.close:()V
       932: goto          952
       935: astore        21
       937: aload         14
       939: aload         21
       941: invokevirtual #54                 // Method java/lang/Throwable.addSuppressed:(Ljava/lang/Throwable;)V
       944: goto          952
       947: aload         13
       949: invokevirtual #52                 // Method dev/architectury/transformer/input/OpenedFileAccess.close:()V
       952: aload         20
       954: athrow
       955: aload         12
       957: invokeinterface #94,  1           // InterfaceMethod java/nio/file/Path.toFile:()Ljava/io/File;
       962: invokevirtual #95                 // Method java/io/File.deleteOnExit:()V
       965: invokestatic  #96                 // Method populateAddUrl:()Ljava/util/function/Consumer;
       968: aload         12
       970: invokeinterface #97,  1           // InterfaceMethod java/nio/file/Path.toUri:()Ljava/net/URI;
       975: invokevirtual #98                 // Method java/net/URI.toURL:()Ljava/net/URL;
       978: invokeinterface #99,  2           // InterfaceMethod java/util/function/Consumer.accept:(Ljava/lang/Object;)V
       983: new           #100                // class dev/architectury/transformer/PathModifyListener
       986: dup
       987: aload         9
       989: invokevirtual #38                 // Method dev/architectury/transformer/TransformerRuntime$PathWithTransformersEntry.getPath:()Ljava/nio/file/Path;
       992: aload         12
       994: aload         9
       996: aload         10
       998: aload         11
      1000: invokedynamic #101,  0            // InvokeDynamic #5:accept:(Ljava/nio/file/Path;Ldev/architectury/transformer/TransformerRuntime$PathWithTransformersEntry;Ljava/util/Map;Ldev/architectury/transformer/input/DirectoryFileAccess;)Ljava/util/function/Consumer;
      1005: invokespecial #102                // Method dev/architectury/transformer/PathModifyListener."<init>":(Ljava/nio/file/Path;Ljava/util/function/Consumer;)V
      1008: pop
      1009: goto          489
      1012: new           #17                 // class java/util/ArrayList
      1015: dup
      1016: ldc           #103                // String java.class.path
      1018: ldc           #104                // String
      1020: invokestatic  #5                  // Method java/lang/System.getProperty:(Ljava/lang/String;Ljava/lang/String;)Ljava/lang/String;
      1023: getstatic     #105                // Field java/io/File.pathSeparator:Ljava/lang/String;
      1026: invokevirtual #106                // Method java/lang/String.split:(Ljava/lang/String;)[Ljava/lang/String;
      1029: invokestatic  #18                 // Method java/util/Arrays.asList:([Ljava/lang/Object;)Ljava/util/List;
      1032: invokespecial #19                 // Method java/util/ArrayList."<init>":(Ljava/util/Collection;)V
      1035: astore        8
      1037: aload         7
      1039: invokeinterface #33,  1           // InterfaceMethod java/util/List.iterator:()Ljava/util/Iterator;
      1044: astore        9
      1046: aload         9
      1048: invokeinterface #34,  1           // InterfaceMethod java/util/Iterator.hasNext:()Z
      1053: ifeq          1099
      1056: aload         9
      1058: invokeinterface #35,  1           // InterfaceMethod java/util/Iterator.next:()Ljava/lang/Object;
      1063: checkcast     #107                // class java/util/Map$Entry
      1066: astore        10
      1068: aload         8
      1070: aload         10
      1072: invokeinterface #108,  1          // InterfaceMethod java/util/Map$Entry.getKey:()Ljava/lang/Object;
      1077: checkcast     #109                // class java/nio/file/Path
      1080: invokeinterface #110,  1          // InterfaceMethod java/nio/file/Path.toAbsolutePath:()Ljava/nio/file/Path;
      1085: invokeinterface #80,  1           // InterfaceMethod java/nio/file/Path.toString:()Ljava/lang/String;
      1090: invokeinterface #72,  2           // InterfaceMethod java/util/List.add:(Ljava/lang/Object;)Z
      1095: pop
      1096: goto          1046
      1099: aload         8
      1101: aload         7
      1103: invokestatic  #111                // Method removeDuplicates:(Ljava/util/List;Ljava/util/List;)V
      1106: ldc           #103                // String java.class.path
      1108: getstatic     #105                // Field java/io/File.pathSeparator:Ljava/lang/String;
      1111: aload         8
      1113: invokestatic  #112                // Method java/lang/String.join:(Ljava/lang/CharSequence;Ljava/lang/Iterable;)Ljava/lang/String;
      1116: invokestatic  #113                // Method java/lang/System.setProperty:(Ljava/lang/String;Ljava/lang/String;)Ljava/lang/String;
      1119: pop
      1120: ldc           #114                // String architectury.main.class
      1122: invokestatic  #22                 // Method java/lang/System.getProperty:(Ljava/lang/String;)Ljava/lang/String;
      1125: iconst_0
      1126: anewarray     #23                 // class java/lang/String
      1129: invokestatic  #24                 // Method java/nio/file/Paths.get:(Ljava/lang/String;[Ljava/lang/String;)Ljava/nio/file/Path;
      1132: astore        9
      1134: new           #23                 // class java/lang/String
      1137: dup
      1138: aload         9
      1140: invokestatic  #25                 // Method java/nio/file/Files.readAllBytes:(Ljava/nio/file/Path;)[B
      1143: getstatic     #26                 // Field java/nio/charset/StandardCharsets.UTF_8:Ljava/nio/charset/Charset;
      1146: invokespecial #27                 // Method java/lang/String."<init>":([BLjava/nio/charset/Charset;)V
      1149: astore        10
      1151: invokestatic  #115                // Method java/lang/invoke/MethodHandles.publicLookup:()Ljava/lang/invoke/MethodHandles$Lookup;
      1154: aload         10
      1156: invokestatic  #116                // Method java/lang/Class.forName:(Ljava/lang/String;)Ljava/lang/Class;
      1159: ldc           #117                // String main
      1161: getstatic     #118                // Field java/lang/Void.TYPE:Ljava/lang/Class;
      1164: ldc           #119                // class "[Ljava/lang/String;"
      1166: invokestatic  #120                // Method java/lang/invoke/MethodType.methodType:(Ljava/lang/Class;Ljava/lang/Class;)Ljava/lang/invoke/MethodType;
      1169: invokevirtual #121                // Method java/lang/invoke/MethodHandles$Lookup.findStatic:(Ljava/lang/Class;Ljava/lang/String;Ljava/lang/invoke/MethodType;)Ljava/lang/invoke/MethodHandle;
      1172: astore        11
      1174: aload         11
      1176: aload_1
      1177: iconst_0
      1178: anewarray     #23                 // class java/lang/String
      1181: invokeinterface #122,  2          // InterfaceMethod java/util/List.toArray:([Ljava/lang/Object;)[Ljava/lang/Object;
      1186: checkcast     #119                // class "[Ljava/lang/String;"
      1189: checkcast     #119                // class "[Ljava/lang/String;"
      1192: invokevirtual #123                // Method java/lang/invoke/MethodHandle.invokeExact:([Ljava/lang/String;)V
      1195: return
      Exception table:
         from    to  target type
           241   246   249   Class java/lang/Throwable
           208   231   269   Class java/lang/Throwable
           208   231   278   any
           290   295   298   Class java/lang/Throwable
           269   280   278   any
           367   372   375   Class java/lang/Throwable
           334   357   395   Class java/lang/Throwable
           334   357   404   any
           416   421   424   Class java/lang/Throwable
           395   406   404   any
           614   619   622   Class java/lang/Throwable
           597   604   642   Class java/lang/Throwable
           597   604   651   any
           663   668   671   Class java/lang/Throwable
           642   653   651   any
           878   883   886   Class java/lang/Throwable
           584   868   906   Class java/lang/Throwable
           584   868   915   any
           927   932   935   Class java/lang/Throwable
           906   917   915   any

  private static void removeDuplicates(java.util.List<java.lang.String>, java.util.List<java.util.Map$Entry<java.nio.file.Path, dev.architectury.transformer.TransformerRuntime$PathWithTransformersEntry>>) throws java.io.IOException;
    Code:
         0: new           #17                 // class java/util/ArrayList
         3: dup
         4: invokespecial #57                 // Method java/util/ArrayList."<init>":()V
         7: astore_2
         8: aload_1
         9: invokeinterface #33,  1           // InterfaceMethod java/util/List.iterator:()Ljava/util/Iterator;
        14: astore_3
        15: aload_3
        16: invokeinterface #34,  1           // InterfaceMethod java/util/Iterator.hasNext:()Z
        21: ifeq          205
        24: aload_3
        25: invokeinterface #35,  1           // InterfaceMethod java/util/Iterator.next:()Ljava/lang/Object;
        30: checkcast     #107                // class java/util/Map$Entry
        33: astore        4
        35: aload         4
        37: invokeinterface #124,  1          // InterfaceMethod java/util/Map$Entry.getValue:()Ljava/lang/Object;
        42: checkcast     #36                 // class dev/architectury/transformer/TransformerRuntime$PathWithTransformersEntry
        45: invokestatic  #125                // Method dev/architectury/transformer/TransformerRuntime$PathWithTransformersEntry.access$000:(Ldev/architectury/transformer/TransformerRuntime$PathWithTransformersEntry;)Ljava/nio/file/Path;
        48: invokestatic  #55                 // Method dev/architectury/transformer/input/OpenedFileAccess.ofJar:(Ljava/nio/file/Path;)Ldev/architectury/transformer/input/OpenedFileAccess;
        51: astore        5
        53: aconst_null
        54: astore        6
        56: new           #126                // class java/util/HashSet
        59: dup
        60: invokespecial #127                // Method java/util/HashSet."<init>":()V
        63: astore        7
        65: aload         5
        67: aload         7
        69: invokedynamic #128,  0            // InvokeDynamic #6:accept:(Ljava/util/Set;)Ljava/util/function/Consumer;
        74: invokevirtual #51                 // Method dev/architectury/transformer/input/OpenedFileAccess.handle:(Ljava/util/function/Consumer;)V
        77: aload_2
        78: aload         7
        80: invokeinterface #72,  2           // InterfaceMethod java/util/List.add:(Ljava/lang/Object;)Z
        85: pop
        86: ldc           #129                // String Temporary jar [%s] contains packages: %s
        88: iconst_2
        89: anewarray     #130                // class java/lang/Object
        92: dup
        93: iconst_0
        94: aload         4
        96: invokeinterface #108,  1          // InterfaceMethod java/util/Map$Entry.getKey:()Ljava/lang/Object;
       101: aastore
       102: dup
       103: iconst_1
       104: ldc           #131                // String ,
       106: aload         7
       108: invokestatic  #112                // Method java/lang/String.join:(Ljava/lang/CharSequence;Ljava/lang/Iterable;)Ljava/lang/String;
       111: aastore
       112: invokestatic  #132                // Method dev/architectury/transformer/util/Logger.debug:(Ljava/lang/String;[Ljava/lang/Object;)V
       115: aload         5
       117: ifnull        202
       120: aload         6
       122: ifnull        145
       125: aload         5
       127: invokevirtual #52                 // Method dev/architectury/transformer/input/OpenedFileAccess.close:()V
       130: goto          202
       133: astore        7
       135: aload         6
       137: aload         7
       139: invokevirtual #54                 // Method java/lang/Throwable.addSuppressed:(Ljava/lang/Throwable;)V
       142: goto          202
       145: aload         5
       147: invokevirtual #52                 // Method dev/architectury/transformer/input/OpenedFileAccess.close:()V
       150: goto          202
       153: astore        7
       155: aload         7
       157: astore        6
       159: aload         7
       161: athrow
       162: astore        8
       164: aload         5
       166: ifnull        199
       169: aload         6
       171: ifnull        194
       174: aload         5
       176: invokevirtual #52                 // Method dev/architectury/transformer/input/OpenedFileAccess.close:()V
       179: goto          199
       182: astore        9
       184: aload         6
       186: aload         9
       188: invokevirtual #54                 // Method java/lang/Throwable.addSuppressed:(Ljava/lang/Throwable;)V
       191: goto          199
       194: aload         5
       196: invokevirtual #52                 // Method dev/architectury/transformer/input/OpenedFileAccess.close:()V
       199: aload         8
       201: athrow
       202: goto          15
       205: aload_0
       206: aload_2
       207: invokedynamic #133,  0            // InvokeDynamic #7:test:(Ljava/util/List;)Ljava/util/function/Predicate;
       212: invokeinterface #134,  2          // InterfaceMethod java/util/List.removeIf:(Ljava/util/function/Predicate;)Z
       217: pop
       218: return
      Exception table:
         from    to  target type
           125   130   133   Class java/lang/Throwable
            56   115   153   Class java/lang/Throwable
            56   115   162   any
           174   179   182   Class java/lang/Throwable
           153   164   162   any

  private static java.util.List<dev.architectury.transformer.TransformerRuntime$PathWithTransformersEntry> parsePathWithTransformersEntries(java.lang.String) throws java.io.IOException;
    Code:
         0: new           #135                // class dev/architectury/transformer/transformers/properties/TransformersReader
         3: dup
         4: new           #136                // class java/io/StringReader
         7: dup
         8: aload_0
         9: invokespecial #137                // Method java/io/StringReader."<init>":(Ljava/lang/String;)V
        12: invokespecial #138                // Method dev/architectury/transformer/transformers/properties/TransformersReader."<init>":(Ljava/io/Reader;)V
        15: astore_2
        16: aconst_null
        17: astore_3
        18: aload_2
        19: invokevirtual #139                // Method dev/architectury/transformer/transformers/properties/TransformersReader.readAll:()Ljava/util/Map;
        22: astore_1
        23: aload_2
        24: ifnull        99
        27: aload_3
        28: ifnull        49
        31: aload_2
        32: invokevirtual #140                // Method dev/architectury/transformer/transformers/properties/TransformersReader.close:()V
        35: goto          99
        38: astore        4
        40: aload_3
        41: aload         4
        43: invokevirtual #54                 // Method java/lang/Throwable.addSuppressed:(Ljava/lang/Throwable;)V
        46: goto          99
        49: aload_2
        50: invokevirtual #140                // Method dev/architectury/transformer/transformers/properties/TransformersReader.close:()V
        53: goto          99
        56: astore        4
        58: aload         4
        60: astore_3
        61: aload         4
        63: athrow
        64: astore        5
        66: aload_2
        67: ifnull        96
        70: aload_3
        71: ifnull        92
        74: aload_2
        75: invokevirtual #140                // Method dev/architectury/transformer/transformers/properties/TransformersReader.close:()V
        78: goto          96
        81: astore        6
        83: aload_3
        84: aload         6
        86: invokevirtual #54                 // Method java/lang/Throwable.addSuppressed:(Ljava/lang/Throwable;)V
        89: goto          96
        92: aload_2
        93: invokevirtual #140                // Method dev/architectury/transformer/transformers/properties/TransformersReader.close:()V
        96: aload         5
        98: athrow
        99: aload_1
       100: invokeinterface #141,  1          // InterfaceMethod java/util/Map.entrySet:()Ljava/util/Set;
       105: invokeinterface #142,  1          // InterfaceMethod java/util/Set.stream:()Ljava/util/stream/Stream;
       110: invokedynamic #143,  0            // InvokeDynamic #8:apply:()Ljava/util/function/Function;
       115: invokeinterface #144,  2          // InterfaceMethod java/util/stream/Stream.map:(Ljava/util/function/Function;)Ljava/util/stream/Stream;
       120: invokestatic  #145                // Method java/util/stream/Collectors.toList:()Ljava/util/stream/Collector;
       123: invokeinterface #146,  2          // InterfaceMethod java/util/stream/Stream.collect:(Ljava/util/stream/Collector;)Ljava/lang/Object;
       128: checkcast     #147                // class java/util/List
       131: areturn
      Exception table:
         from    to  target type
            31    35    38   Class java/lang/Throwable
            18    23    56   Class java/lang/Throwable
            18    23    64   any
            74    78    81   Class java/lang/Throwable
            56    66    64   any

  private static void redefineClasses(java.lang.String, java.util.Map<java.lang.String, byte[]>) throws java.lang.Exception;
    Code:
         0: invokestatic  #148                // Method dev/architectury/transformer/agent/TransformerAgent.getInstrumentation:()Ljava/lang/instrument/Instrumentation;
         3: invokeinterface #149,  1          // InterfaceMethod java/lang/instrument/Instrumentation.getAllLoadedClasses:()[Ljava/lang/Class;
         8: astore_2
         9: new           #17                 // class java/util/ArrayList
        12: dup
        13: invokespecial #57                 // Method java/util/ArrayList."<init>":()V
        16: astore_3
        17: aload_1
        18: aload_2
        19: aload_3
        20: invokedynamic #150,  0            // InvokeDynamic #9:accept:([Ljava/lang/Class;Ljava/util/List;)Ljava/util/function/BiConsumer;
        25: invokeinterface #151,  2          // InterfaceMethod java/util/Map.forEach:(Ljava/util/function/BiConsumer;)V
        30: aload_3
        31: invokeinterface #152,  1          // InterfaceMethod java/util/List.isEmpty:()Z
        36: ifne          81
        39: aload_3
        40: invokedynamic #153,  0            // InvokeDynamic #10:doThing:(Ljava/util/List;)Ldev/architectury/transformer/Transform$DoThing;
        45: new           #8                  // class java/lang/StringBuilder
        48: dup
        49: invokespecial #9                  // Method java/lang/StringBuilder."<init>":()V
        52: ldc           #154                // String Redefined
        54: invokevirtual #11                 // Method java/lang/StringBuilder.append:(Ljava/lang/String;)Ljava/lang/StringBuilder;
        57: aload_3
        58: invokeinterface #77,  1           // InterfaceMethod java/util/List.size:()I
        63: invokevirtual #78                 // Method java/lang/StringBuilder.append:(I)Ljava/lang/StringBuilder;
        66: ldc           #155                // String  class(es) from
        68: invokevirtual #11                 // Method java/lang/StringBuilder.append:(Ljava/lang/String;)Ljava/lang/StringBuilder;
        71: aload_0
        72: invokevirtual #11                 // Method java/lang/StringBuilder.append:(Ljava/lang/String;)Ljava/lang/StringBuilder;
        75: invokevirtual #15                 // Method java/lang/StringBuilder.toString:()Ljava/lang/String;
        78: invokestatic  #156                // Method dev/architectury/transformer/Transform.logTime:(Ldev/architectury/transformer/Transform$DoThing;Ljava/lang/String;)V
        81: return

  private static void applyProperties() throws java.io.IOException;
    Code:
         0: ldc           #157                // String architectury.properties
         2: invokestatic  #22                 // Method java/lang/System.getProperty:(Ljava/lang/String;)Ljava/lang/String;
         5: iconst_0
         6: anewarray     #23                 // class java/lang/String
         9: invokestatic  #24                 // Method java/nio/file/Paths.get:(Ljava/lang/String;[Ljava/lang/String;)Ljava/nio/file/Path;
        12: astore_0
        13: new           #158                // class java/util/Properties
        16: dup
        17: invokespecial #159                // Method java/util/Properties."<init>":()V
        20: astore_1
        21: aload_0
        22: getstatic     #26                 // Field java/nio/charset/StandardCharsets.UTF_8:Ljava/nio/charset/Charset;
        25: invokestatic  #160                // Method java/nio/file/Files.newBufferedReader:(Ljava/nio/file/Path;Ljava/nio/charset/Charset;)Ljava/io/BufferedReader;
        28: astore_2
        29: aconst_null
        30: astore_3
        31: aload_1
        32: aload_2
        33: invokevirtual #161                // Method java/util/Properties.load:(Ljava/io/Reader;)V
        36: aload_2
        37: ifnull        112
        40: aload_3
        41: ifnull        62
        44: aload_2
        45: invokevirtual #162                // Method java/io/Reader.close:()V
        48: goto          112
        51: astore        4
        53: aload_3
        54: aload         4
        56: invokevirtual #54                 // Method java/lang/Throwable.addSuppressed:(Ljava/lang/Throwable;)V
        59: goto          112
        62: aload_2
        63: invokevirtual #162                // Method java/io/Reader.close:()V
        66: goto          112
        69: astore        4
        71: aload         4
        73: astore_3
        74: aload         4
        76: athrow
        77: astore        5
        79: aload_2
        80: ifnull        109
        83: aload_3
        84: ifnull        105
        87: aload_2
        88: invokevirtual #162                // Method java/io/Reader.close:()V
        91: goto          109
        94: astore        6
        96: aload_3
        97: aload         6
        99: invokevirtual #54                 // Method java/lang/Throwable.addSuppressed:(Ljava/lang/Throwable;)V
       102: goto          109
       105: aload_2
       106: invokevirtual #162                // Method java/io/Reader.close:()V
       109: aload         5
       111: athrow
       112: aload_1
       113: invokedynamic #163,  0            // InvokeDynamic #11:accept:()Ljava/util/function/BiConsumer;
       118: invokevirtual #164                // Method java/util/Properties.forEach:(Ljava/util/function/BiConsumer;)V
       121: return
      Exception table:
         from    to  target type
            44    48    51   Class java/lang/Throwable
            31    36    69   Class java/lang/Throwable
            31    36    77   any
            87    91    94   Class java/lang/Throwable
            69    79    77   any

  private static void doInstrumentationStuff();
    Code:
         0: iconst_1
         1: istore_0
         2: new           #88                 // class dev/architectury/transformer/transformers/base/edit/SimpleTransformerContext
         5: dup
         6: invokedynamic #165,  0            // InvokeDynamic #12:accept:()Ljava/util/function/Consumer;
        11: iconst_0
        12: iconst_1
        13: iconst_0
        14: invokespecial #90                 // Method dev/architectury/transformer/transformers/base/edit/SimpleTransformerContext."<init>":(Ljava/util/function/Consumer;ZZZ)V
        17: astore_2
        18: iload_0
        19: ifeq          41
        22: new           #166                // class dev/architectury/transformer/handler/TinyRemapperPreparedTransformerHandler
        25: dup
        26: getstatic     #62                 // Field classpathProvider:Ldev/architectury/transformer/transformers/classpath/ReadClasspathProvider;
        29: aload_2
        30: iconst_0
        31: invokespecial #167                // Method dev/architectury/transformer/handler/TinyRemapperPreparedTransformerHandler."<init>":(Ldev/architectury/transformer/transformers/classpath/ReadClasspathProvider;Ldev/architectury/transformer/transformers/base/edit/TransformerContext;Z)V
        34: invokevirtual #168                // Method dev/architectury/transformer/handler/TinyRemapperPreparedTransformerHandler.asThreadLocked:()Ldev/architectury/transformer/handler/TransformHandler;
        37: astore_1
        38: goto          57
        41: new           #169                // class dev/architectury/transformer/handler/SimpleTransformerHandler
        44: dup
        45: getstatic     #62                 // Field classpathProvider:Ldev/architectury/transformer/transformers/classpath/ReadClasspathProvider;
        48: aload_2
        49: iconst_0
        50: invokespecial #170                // Method dev/architectury/transformer/handler/SimpleTransformerHandler."<init>":(Ldev/architectury/transformer/transformers/classpath/ReadClasspathProvider;Ldev/architectury/transformer/transformers/base/edit/TransformerContext;Z)V
        53: invokevirtual #171                // Method dev/architectury/transformer/handler/SimpleTransformerHandler.asThreadLocked:()Ldev/architectury/transformer/handler/TransformHandler;
        56: astore_1
        57: goto          70
        60: astore_2
        61: new           #173                // class java/lang/RuntimeException
        64: dup
        65: aload_2
        66: invokespecial #174                // Method java/lang/RuntimeException."<init>":(Ljava/lang/Throwable;)V
        69: athrow
        70: invokestatic  #148                // Method dev/architectury/transformer/agent/TransformerAgent.getInstrumentation:()Ljava/lang/instrument/Instrumentation;
        73: astore_2
        74: aload_2
        75: new           #175                // class dev/architectury/transformer/ClassTransformerFileAccess
        78: dup
        79: aload_1
        80: getstatic     #176                // Field CLASSES_TO_TRANSFORM:Ljava/util/Map;
        83: dup
        84: invokevirtual #177                // Method java/lang/Object.getClass:()Ljava/lang/Class;
        87: pop
        88: invokedynamic #178,  0            // InvokeDynamic #13:apply:(Ljava/util/Map;)Ljava/util/function/Function;
        93: invokespecial #179                // Method dev/architectury/transformer/ClassTransformerFileAccess."<init>":(Ldev/architectury/transformer/handler/TransformHandler;Ljava/util/function/Function;)V
        96: aload_2
        97: invokeinterface #180,  1          // InterfaceMethod java/lang/instrument/Instrumentation.isRedefineClassesSupported:()Z
       102: invokeinterface #181,  3          // InterfaceMethod java/lang/instrument/Instrumentation.addTransformer:(Ljava/lang/instrument/ClassFileTransformer;Z)V
       107: return
      Exception table:
         from    to  target type
             2    57    60   Class java/lang/Exception

  private static java.util.function.Consumer<java.net.URL> populateAddUrl();
    Code:
         0: invokestatic  #182                // Method java/lang/ClassLoader.getSystemClassLoader:()Ljava/lang/ClassLoader;
         3: instanceof    #183                // class java/net/URLClassLoader
         6: ifeq          15
         9: invokedynamic #184,  0            // InvokeDynamic #14:accept:()Ljava/util/function/Consumer;
        14: areturn
        15: invokedynamic #185,  0            // InvokeDynamic #15:accept:()Ljava/util/function/Consumer;
        20: areturn

  private static void lambda$populateAddUrl$18(java.net.URL);
    Code:
         0: invokestatic  #148                // Method dev/architectury/transformer/agent/TransformerAgent.getInstrumentation:()Ljava/lang/instrument/Instrumentation;
         3: new           #186                // class java/util/jar/JarFile
         6: dup
         7: new           #187                // class java/io/File
        10: dup
        11: aload_0
        12: invokevirtual #188                // Method java/net/URL.toURI:()Ljava/net/URI;
        15: invokespecial #189                // Method java/io/File."<init>":(Ljava/net/URI;)V
        18: invokespecial #190                // Method java/util/jar/JarFile."<init>":(Ljava/io/File;)V
        21: invokeinterface #191,  2          // InterfaceMethod java/lang/instrument/Instrumentation.appendToSystemClassLoaderSearch:(Ljava/util/jar/JarFile;)V
        26: goto          39
        29: astore_1
        30: new           #173                // class java/lang/RuntimeException
        33: dup
        34: aload_1
        35: invokespecial #174                // Method java/lang/RuntimeException."<init>":(Ljava/lang/Throwable;)V
        38: athrow
        39: return
      Exception table:
         from    to  target type
             0    26    29   Class java/lang/Throwable

  private static void lambda$populateAddUrl$17(java.net.URL);
    Code:
         0: ldc           #183                // class java/net/URLClassLoader
         2: ldc           #192                // String addURL
         4: iconst_1
         5: anewarray     #193                // class java/lang/Class
         8: dup
         9: iconst_0
        10: ldc           #194                // class java/net/URL
        12: aastore
        13: invokevirtual #195                // Method java/lang/Class.getDeclaredMethod:(Ljava/lang/String;[Ljava/lang/Class;)Ljava/lang/reflect/Method;
        16: astore_1
        17: aload_1
        18: iconst_1
        19: invokevirtual #196                // Method java/lang/reflect/Method.setAccessible:(Z)V
        22: aload_1
        23: invokestatic  #182                // Method java/lang/ClassLoader.getSystemClassLoader:()Ljava/lang/ClassLoader;
        26: iconst_1
        27: anewarray     #130                // class java/lang/Object
        30: dup
        31: iconst_0
        32: aload_0
        33: aastore
        34: invokevirtual #197                // Method java/lang/reflect/Method.invoke:(Ljava/lang/Object;[Ljava/lang/Object;)Ljava/lang/Object;
        37: pop
        38: goto          51
        41: astore_1
        42: new           #173                // class java/lang/RuntimeException
        45: dup
        46: aload_1
        47: invokespecial #174                // Method java/lang/RuntimeException."<init>":(Ljava/lang/Throwable;)V
        50: athrow
        51: return
      Exception table:
         from    to  target type
             0    38    41   Class java/lang/Throwable

  private static void lambda$doInstrumentationStuff$16(java.lang.String[]);
    Code:
         0: return

  private static void lambda$applyProperties$15(java.lang.Object, java.lang.Object);
    Code:
         0: aload_0
         1: checkcast     #23                 // class java/lang/String
         4: aload_1
         5: checkcast     #23                 // class java/lang/String
         8: invokestatic  #113                // Method java/lang/System.setProperty:(Ljava/lang/String;Ljava/lang/String;)Ljava/lang/String;
        11: pop
        12: return

  private static void lambda$redefineClasses$14(java.util.List) throws java.lang.Exception;
    Code:
         0: invokestatic  #148                // Method dev/architectury/transformer/agent/TransformerAgent.getInstrumentation:()Ljava/lang/instrument/Instrumentation;
         3: aload_0
         4: iconst_0
         5: anewarray     #198                // class java/lang/instrument/ClassDefinition
         8: invokeinterface #122,  2          // InterfaceMethod java/util/List.toArray:([Ljava/lang/Object;)[Ljava/lang/Object;
        13: checkcast     #199                // class "[Ljava/lang/instrument/ClassDefinition;"
        16: invokeinterface #200,  2          // InterfaceMethod java/lang/instrument/Instrumentation.redefineClasses:([Ljava/lang/instrument/ClassDefinition;)V
        21: return

  private static void lambda$redefineClasses$13(java.lang.Class[], java.util.List, java.lang.String, byte[]);
    Code:
         0: aload_2
         1: bipush        47
         3: bipush        46
         5: invokevirtual #201                // Method java/lang/String.replace:(CC)Ljava/lang/String;
         8: astore        4
        10: aload_0
        11: invokestatic  #202                // Method java/util/Arrays.stream:([Ljava/lang/Object;)Ljava/util/stream/Stream;
        14: invokedynamic #203,  0            // InvokeDynamic #16:test:()Ljava/util/function/Predicate;
        19: invokeinterface #204,  2          // InterfaceMethod java/util/stream/Stream.filter:(Ljava/util/function/Predicate;)Ljava/util/stream/Stream;
        24: aload         4
        26: invokedynamic #205,  0            // InvokeDynamic #17:test:(Ljava/lang/String;)Ljava/util/function/Predicate;
        31: invokeinterface #204,  2          // InterfaceMethod java/util/stream/Stream.filter:(Ljava/util/function/Predicate;)Ljava/util/stream/Stream;
        36: invokeinterface #206,  1          // InterfaceMethod java/util/stream/Stream.iterator:()Ljava/util/Iterator;
        41: astore        5
        43: aload         5
        45: invokeinterface #34,  1           // InterfaceMethod java/util/Iterator.hasNext:()Z
        50: ifeq          122
        53: aload         5
        55: invokeinterface #35,  1           // InterfaceMethod java/util/Iterator.next:()Ljava/lang/Object;
        60: checkcast     #193                // class java/lang/Class
        63: astore        6
        65: aload         6
        67: invokevirtual #207                // Method java/lang/Class.getClassLoader:()Ljava/lang/ClassLoader;
        70: invokestatic  #182                // Method java/lang/ClassLoader.getSystemClassLoader:()Ljava/lang/ClassLoader;
        73: if_acmpne     79
        76: goto          43
        79: new           #8                  // class java/lang/StringBuilder
        82: dup
        83: invokespecial #9                  // Method java/lang/StringBuilder."<init>":()V
        86: ldc           #208                // String Redefining
        88: invokevirtual #11                 // Method java/lang/StringBuilder.append:(Ljava/lang/String;)Ljava/lang/StringBuilder;
        91: aload         4
        93: invokevirtual #11                 // Method java/lang/StringBuilder.append:(Ljava/lang/String;)Ljava/lang/StringBuilder;
        96: invokevirtual #15                 // Method java/lang/StringBuilder.toString:()Ljava/lang/String;
        99: invokestatic  #84                 // Method dev/architectury/transformer/util/Logger.debug:(Ljava/lang/String;)V
       102: aload_1
       103: new           #198                // class java/lang/instrument/ClassDefinition
       106: dup
       107: aload         6
       109: aload_3
       110: invokespecial #209                // Method java/lang/instrument/ClassDefinition."<init>":(Ljava/lang/Class;[B)V
       113: invokeinterface #72,  2           // InterfaceMethod java/util/List.add:(Ljava/lang/Object;)Z
       118: pop
       119: goto          43
       122: return

  private static boolean lambda$null$12(java.lang.String, java.lang.Class);
    Code:
         0: aload_1
         1: invokevirtual #210                // Method java/lang/Class.getName:()Ljava/lang/String;
         4: aload_0
         5: invokestatic  #211                // Method java/util/Objects.equals:(Ljava/lang/Object;Ljava/lang/Object;)Z
         8: ireturn

  private static boolean lambda$null$11(java.lang.Class);
    Code:
         0: aload_0
         1: invokevirtual #207                // Method java/lang/Class.getClassLoader:()Ljava/lang/ClassLoader;
         4: invokestatic  #182                // Method java/lang/ClassLoader.getSystemClassLoader:()Ljava/lang/ClassLoader;
         7: if_acmpeq     14
        10: iconst_1
        11: goto          15
        14: iconst_0
        15: ireturn

  private static dev.architectury.transformer.TransformerRuntime$PathWithTransformersEntry lambda$parsePathWithTransformersEntries$10(java.util.Map$Entry);
    Code:
         0: new           #36                 // class dev/architectury/transformer/TransformerRuntime$PathWithTransformersEntry
         3: dup
         4: aload_0
         5: invokeinterface #108,  1          // InterfaceMethod java/util/Map$Entry.getKey:()Ljava/lang/Object;
        10: checkcast     #109                // class java/nio/file/Path
        13: aload_0
        14: invokeinterface #124,  1          // InterfaceMethod java/util/Map$Entry.getValue:()Ljava/lang/Object;
        19: checkcast     #147                // class java/util/List
        22: invokeinterface #212,  1          // InterfaceMethod java/util/List.stream:()Ljava/util/stream/Stream;
        27: invokedynamic #213,  0            // InvokeDynamic #18:apply:()Ljava/util/function/Function;
        32: invokeinterface #144,  2          // InterfaceMethod java/util/stream/Stream.map:(Ljava/util/function/Function;)Ljava/util/stream/Stream;
        37: invokestatic  #145                // Method java/util/stream/Collectors.toList:()Ljava/util/stream/Collector;
        40: invokeinterface #146,  2          // InterfaceMethod java/util/stream/Stream.collect:(Ljava/util/stream/Collector;)Ljava/lang/Object;
        45: checkcast     #147                // class java/util/List
        48: invokespecial #214                // Method dev/architectury/transformer/TransformerRuntime$PathWithTransformersEntry."<init>":(Ljava/nio/file/Path;Ljava/util/List;)V
        51: areturn

  private static boolean lambda$removeDuplicates$9(java.util.List, java.lang.String);
    Code:
         0: aload_1
         1: iconst_0
         2: anewarray     #23                 // class java/lang/String
         5: invokestatic  #24                 // Method java/nio/file/Paths.get:(Ljava/lang/String;[Ljava/lang/String;)Ljava/nio/file/Path;
         8: astore_2
         9: aload_2
        10: iconst_0
        11: anewarray     #46                 // class java/nio/file/LinkOption
        14: invokestatic  #47                 // Method java/nio/file/Files.isDirectory:(Ljava/nio/file/Path;[Ljava/nio/file/LinkOption;)Z
        17: ifeq          306
        20: aload_2
        21: invokestatic  #48                 // Method dev/architectury/transformer/input/OpenedFileAccess.ofDirectory:(Ljava/nio/file/Path;)Ldev/architectury/transformer/input/OpenedFileAccess;
        24: astore_3
        25: aconst_null
        26: astore        4
        28: new           #126                // class java/util/HashSet
        31: dup
        32: invokespecial #127                // Method java/util/HashSet."<init>":()V
        35: astore        5
        37: aload_3
        38: aload_2
        39: aload         5
        41: invokedynamic #215,  0            // InvokeDynamic #19:accept:(Ljava/nio/file/Path;Ljava/util/Set;)Ljava/util/function/Consumer;
        46: invokevirtual #51                 // Method dev/architectury/transformer/input/OpenedFileAccess.handle:(Ljava/util/function/Consumer;)V
        49: ldc           #216                // String Classpath entry [%s] contains packages: %s
        51: iconst_2
        52: anewarray     #130                // class java/lang/Object
        55: dup
        56: iconst_0
        57: aload_1
        58: aastore
        59: dup
        60: iconst_1
        61: ldc           #131                // String ,
        63: aload         5
        65: invokestatic  #112                // Method java/lang/String.join:(Ljava/lang/CharSequence;Ljava/lang/Iterable;)Ljava/lang/String;
        68: aastore
        69: invokestatic  #132                // Method dev/architectury/transformer/util/Logger.debug:(Ljava/lang/String;[Ljava/lang/Object;)V
        72: aload         5
        74: invokeinterface #217,  1          // InterfaceMethod java/util/Set.isEmpty:()Z
        79: ifeq          120
        82: iconst_0
        83: istore        6
        85: aload_3
        86: ifnull        117
        89: aload         4
        91: ifnull        113
        94: aload_3
        95: invokevirtual #52                 // Method dev/architectury/transformer/input/OpenedFileAccess.close:()V
        98: goto          117
       101: astore        7
       103: aload         4
       105: aload         7
       107: invokevirtual #54                 // Method java/lang/Throwable.addSuppressed:(Ljava/lang/Throwable;)V
       110: goto          117
       113: aload_3
       114: invokevirtual #52                 // Method dev/architectury/transformer/input/OpenedFileAccess.close:()V
       117: iload         6
       119: ireturn
       120: aload_0
       121: invokeinterface #33,  1           // InterfaceMethod java/util/List.iterator:()Ljava/util/Iterator;
       126: astore        6
       128: aload         6
       130: invokeinterface #34,  1           // InterfaceMethod java/util/Iterator.hasNext:()Z
       135: ifeq          225
       138: aload         6
       140: invokeinterface #35,  1           // InterfaceMethod java/util/Iterator.next:()Ljava/lang/Object;
       145: checkcast     #218                // class java/util/Set
       148: astore        7
       150: aload         7
       152: aload         5
       154: invokeinterface #219,  2          // InterfaceMethod java/util/Set.equals:(Ljava/lang/Object;)Z
       159: ifeq          222
       162: new           #8                  // class java/lang/StringBuilder
       165: dup
       166: invokespecial #9                  // Method java/lang/StringBuilder."<init>":()V
       169: ldc           #220                // String Removing duplicate classpath entry:
       171: invokevirtual #11                 // Method java/lang/StringBuilder.append:(Ljava/lang/String;)Ljava/lang/StringBuilder;
       174: aload_1
       175: invokevirtual #11                 // Method java/lang/StringBuilder.append:(Ljava/lang/String;)Ljava/lang/StringBuilder;
       178: invokevirtual #15                 // Method java/lang/StringBuilder.toString:()Ljava/lang/String;
       181: invokestatic  #16                 // Method dev/architectury/transformer/util/Logger.info:(Ljava/lang/String;)V
       184: iconst_1
       185: istore        8
       187: aload_3
       188: ifnull        219
       191: aload         4
       193: ifnull        215
       196: aload_3
       197: invokevirtual #52                 // Method dev/architectury/transformer/input/OpenedFileAccess.close:()V
       200: goto          219
       203: astore        9
       205: aload         4
       207: aload         9
       209: invokevirtual #54                 // Method java/lang/Throwable.addSuppressed:(Ljava/lang/Throwable;)V
       212: goto          219
       215: aload_3
       216: invokevirtual #52                 // Method dev/architectury/transformer/input/OpenedFileAccess.close:()V
       219: iload         8
       221: ireturn
       222: goto          128
       225: aload_3
       226: ifnull        306
       229: aload         4
       231: ifnull        253
       234: aload_3
       235: invokevirtual #52                 // Method dev/architectury/transformer/input/OpenedFileAccess.close:()V
       238: goto          306
       241: astore        5
       243: aload         4
       245: aload         5
       247: invokevirtual #54                 // Method java/lang/Throwable.addSuppressed:(Ljava/lang/Throwable;)V
       250: goto          306
       253: aload_3
       254: invokevirtual #52                 // Method dev/architectury/transformer/input/OpenedFileAccess.close:()V
       257: goto          306
       260: astore        5
       262: aload         5
       264: astore        4
       266: aload         5
       268: athrow
       269: astore        10
       271: aload_3
       272: ifnull        303
       275: aload         4
       277: ifnull        299
       280: aload_3
       281: invokevirtual #52                 // Method dev/architectury/transformer/input/OpenedFileAccess.close:()V
       284: goto          303
       287: astore        11
       289: aload         4
       291: aload         11
       293: invokevirtual #54                 // Method java/lang/Throwable.addSuppressed:(Ljava/lang/Throwable;)V
       296: goto          303
       299: aload_3
       300: invokevirtual #52                 // Method dev/architectury/transformer/input/OpenedFileAccess.close:()V
       303: aload         10
       305: athrow
       306: goto          314
       309: astore_2
       310: aload_2
       311: invokevirtual #221                // Method java/lang/Throwable.printStackTrace:()V
       314: iconst_0
       315: ireturn
      Exception table:
         from    to  target type
            94    98   101   Class java/lang/Throwable
           196   200   203   Class java/lang/Throwable
           234   238   241   Class java/lang/Throwable
            28    85   260   Class java/lang/Throwable
           120   187   260   Class java/lang/Throwable
           222   225   260   Class java/lang/Throwable
            28    85   269   any
           120   187   269   any
           222   225   269   any
           280   284   287   Class java/lang/Throwable
           260   271   269   any
             0   117   309   Class java/lang/Throwable
           120   219   309   Class java/lang/Throwable
           222   306   309   Class java/lang/Throwable

  private static void lambda$null$8(java.nio.file.Path, java.util.Set, java.lang.String);
    Code:
         0: aload_0
         1: aload_2
         2: iconst_0
         3: anewarray     #23                 // class java/lang/String
         6: invokestatic  #24                 // Method java/nio/file/Paths.get:(Ljava/lang/String;[Ljava/lang/String;)Ljava/nio/file/Path;
         9: invokeinterface #222,  2          // InterfaceMethod java/nio/file/Path.relativize:(Ljava/nio/file/Path;)Ljava/nio/file/Path;
        14: invokeinterface #80,  1           // InterfaceMethod java/nio/file/Path.toString:()Ljava/lang/String;
        19: invokestatic  #223                // Method dev/architectury/transformer/Transform.trimLeadingSlash:(Ljava/lang/String;)Ljava/lang/String;
        22: astore_3
        23: aload_3
        24: ldc           #224                // String .class
        26: invokevirtual #225                // Method java/lang/String.endsWith:(Ljava/lang/String;)Z
        29: ifeq          61
        32: aload_3
        33: iconst_0
        34: aload_3
        35: bipush        47
        37: invokevirtual #226                // Method java/lang/String.lastIndexOf:(I)I
        40: invokevirtual #227                // Method java/lang/String.substring:(II)Ljava/lang/String;
        43: bipush        47
        45: bipush        46
        47: invokevirtual #201                // Method java/lang/String.replace:(CC)Ljava/lang/String;
        50: astore        4
        52: aload_1
        53: aload         4
        55: invokeinterface #45,  2           // InterfaceMethod java/util/Set.add:(Ljava/lang/Object;)Z
        60: pop
        61: return

  private static void lambda$removeDuplicates$7(java.util.Set, java.lang.String);
    Code:
         0: aload_1
         1: ldc           #224                // String .class
         3: invokevirtual #225                // Method java/lang/String.endsWith:(Ljava/lang/String;)Z
         6: ifeq          42
         9: aload_1
        10: invokestatic  #223                // Method dev/architectury/transformer/Transform.trimLeadingSlash:(Ljava/lang/String;)Ljava/lang/String;
        13: iconst_0
        14: aload_1
        15: invokestatic  #223                // Method dev/architectury/transformer/Transform.trimLeadingSlash:(Ljava/lang/String;)Ljava/lang/String;
        18: bipush        47
        20: invokevirtual #226                // Method java/lang/String.lastIndexOf:(I)I
        23: invokevirtual #227                // Method java/lang/String.substring:(II)Ljava/lang/String;
        26: bipush        47
        28: bipush        46
        30: invokevirtual #201                // Method java/lang/String.replace:(CC)Ljava/lang/String;
        33: astore_2
        34: aload_0
        35: aload_2
        36: invokeinterface #45,  2           // InterfaceMethod java/util/Set.add:(Ljava/lang/Object;)Z
        41: pop
        42: return

  private static void lambda$main$6(java.nio.file.Path, dev.architectury.transformer.TransformerRuntime$PathWithTransformersEntry, java.util.Map, dev.architectury.transformer.input.DirectoryFileAccess, java.nio.file.Path);
    Code:
         0: aload_0
         1: invokestatic  #55                 // Method dev/architectury/transformer/input/OpenedFileAccess.ofJar:(Ljava/nio/file/Path;)Ldev/architectury/transformer/input/OpenedFileAccess;
         4: astore        5
         6: aconst_null
         7: astore        6
         9: ldc2_w        #228                // long 4000l
        12: invokestatic  #230                // Method java/lang/Thread.sleep:(J)V
        15: ldc           #231                // String os.name
        17: invokestatic  #22                 // Method java/lang/System.getProperty:(Ljava/lang/String;)Ljava/lang/String;
        20: ldc           #232                // String Windows
        22: invokevirtual #233                // Method java/lang/String.startsWith:(Ljava/lang/String;)Z
        25: ifne          33
        28: aload_0
        29: invokestatic  #73                 // Method java/nio/file/Files.deleteIfExists:(Ljava/nio/file/Path;)Z
        32: pop
        33: aload_1
        34: invokevirtual #38                 // Method dev/architectury/transformer/TransformerRuntime$PathWithTransformersEntry.getPath:()Ljava/nio/file/Path;
        37: invokestatic  #55                 // Method dev/architectury/transformer/input/OpenedFileAccess.ofJar:(Ljava/nio/file/Path;)Ldev/architectury/transformer/input/OpenedFileAccess;
        40: astore        7
        42: aconst_null
        43: astore        8
        45: aload         7
        47: aload         5
        49: invokevirtual #74                 // Method dev/architectury/transformer/input/OpenedFileAccess.copyTo:(Ldev/architectury/transformer/input/FileAccess;)V
        52: aload         7
        54: ifnull        139
        57: aload         8
        59: ifnull        82
        62: aload         7
        64: invokevirtual #52                 // Method dev/architectury/transformer/input/OpenedFileAccess.close:()V
        67: goto          139
        70: astore        9
        72: aload         8
        74: aload         9
        76: invokevirtual #54                 // Method java/lang/Throwable.addSuppressed:(Ljava/lang/Throwable;)V
        79: goto          139
        82: aload         7
        84: invokevirtual #52                 // Method dev/architectury/transformer/input/OpenedFileAccess.close:()V
        87: goto          139
        90: astore        9
        92: aload         9
        94: astore        8
        96: aload         9
        98: athrow
        99: astore        10
       101: aload         7
       103: ifnull        136
       106: aload         8
       108: ifnull        131
       111: aload         7
       113: invokevirtual #52                 // Method dev/architectury/transformer/input/OpenedFileAccess.close:()V
       116: goto          136
       119: astore        11
       121: aload         8
       123: aload         11
       125: invokevirtual #54                 // Method java/lang/Throwable.addSuppressed:(Ljava/lang/Throwable;)V
       128: goto          136
       131: aload         7
       133: invokevirtual #52                 // Method dev/architectury/transformer/input/OpenedFileAccess.close:()V
       136: aload         10
       138: athrow
       139: new           #8                  // class java/lang/StringBuilder
       142: dup
       143: invokespecial #9                  // Method java/lang/StringBuilder."<init>":()V
       146: ldc           #234                // String Detected File Modification at
       148: invokevirtual #11                 // Method java/lang/StringBuilder.append:(Ljava/lang/String;)Ljava/lang/StringBuilder;
       151: aload         4
       153: invokeinterface #235,  1          // InterfaceMethod java/nio/file/Path.getFileName:()Ljava/nio/file/Path;
       158: invokeinterface #80,  1           // InterfaceMethod java/nio/file/Path.toString:()Ljava/lang/String;
       163: invokevirtual #11                 // Method java/lang/StringBuilder.append:(Ljava/lang/String;)Ljava/lang/StringBuilder;
       166: invokevirtual #15                 // Method java/lang/StringBuilder.toString:()Ljava/lang/String;
       169: invokestatic  #16                 // Method dev/architectury/transformer/util/Logger.info:(Ljava/lang/String;)V
       172: new           #64                 // class java/util/HashMap
       175: dup
       176: invokespecial #65                 // Method java/util/HashMap."<init>":()V
       179: astore        7
       181: new           #8                  // class java/lang/StringBuilder
       184: dup
       185: invokespecial #9                  // Method java/lang/StringBuilder."<init>":()V
       188: ldc           #75                 // String Transforming
       190: invokevirtual #11                 // Method java/lang/StringBuilder.append:(Ljava/lang/String;)Ljava/lang/StringBuilder;
       193: aload_1
       194: invokevirtual #76                 // Method dev/architectury/transformer/TransformerRuntime$PathWithTransformersEntry.getTransformers:()Ljava/util/List;
       197: invokeinterface #77,  1           // InterfaceMethod java/util/List.size:()I
       202: invokevirtual #78                 // Method java/lang/StringBuilder.append:(I)Ljava/lang/StringBuilder;
       205: ldc           #79                 // String  transformer(s) from
       207: invokevirtual #11                 // Method java/lang/StringBuilder.append:(Ljava/lang/String;)Ljava/lang/StringBuilder;
       210: aload_1
       211: invokevirtual #38                 // Method dev/architectury/transformer/TransformerRuntime$PathWithTransformersEntry.getPath:()Ljava/nio/file/Path;
       214: invokeinterface #80,  1           // InterfaceMethod java/nio/file/Path.toString:()Ljava/lang/String;
       219: invokevirtual #11                 // Method java/lang/StringBuilder.append:(Ljava/lang/String;)Ljava/lang/StringBuilder;
       222: ldc           #81                 // String  to
       224: invokevirtual #11                 // Method java/lang/StringBuilder.append:(Ljava/lang/String;)Ljava/lang/StringBuilder;
       227: aload_0
       228: invokevirtual #82                 // Method java/lang/StringBuilder.append:(Ljava/lang/Object;)Ljava/lang/StringBuilder;
       231: ldc           #83                 // String :
       233: invokevirtual #11                 // Method java/lang/StringBuilder.append:(Ljava/lang/String;)Ljava/lang/StringBuilder;
       236: invokevirtual #15                 // Method java/lang/StringBuilder.toString:()Ljava/lang/String;
       239: invokestatic  #84                 // Method dev/architectury/transformer/util/Logger.debug:(Ljava/lang/String;)V
       242: aload_1
       243: invokevirtual #76                 // Method dev/architectury/transformer/TransformerRuntime$PathWithTransformersEntry.getTransformers:()Ljava/util/List;
       246: invokeinterface #33,  1           // InterfaceMethod java/util/List.iterator:()Ljava/util/Iterator;
       251: astore        8
       253: aload         8
       255: invokeinterface #34,  1           // InterfaceMethod java/util/Iterator.hasNext:()Z
       260: ifeq          304
       263: aload         8
       265: invokeinterface #35,  1           // InterfaceMethod java/util/Iterator.next:()Ljava/lang/Object;
       270: checkcast     #85                 // class dev/architectury/transformer/Transformer
       273: astore        9
       275: new           #8                  // class java/lang/StringBuilder
       278: dup
       279: invokespecial #9                  // Method java/lang/StringBuilder."<init>":()V
       282: ldc           #86                 // String  -
       284: invokevirtual #11                 // Method java/lang/StringBuilder.append:(Ljava/lang/String;)Ljava/lang/StringBuilder;
       287: aload         9
       289: invokevirtual #87                 // Method java/lang/Object.toString:()Ljava/lang/String;
       292: invokevirtual #11                 // Method java/lang/StringBuilder.append:(Ljava/lang/String;)Ljava/lang/StringBuilder;
       295: invokevirtual #15                 // Method java/lang/StringBuilder.toString:()Ljava/lang/String;
       298: invokestatic  #84                 // Method dev/architectury/transformer/util/Logger.debug:(Ljava/lang/String;)V
       301: goto          253
       304: new           #64                 // class java/util/HashMap
       307: dup
       308: aload_2
       309: invokespecial #236                // Method java/util/HashMap."<init>":(Ljava/util/Map;)V
       312: astore        8
       314: new           #88                 // class dev/architectury/transformer/transformers/base/edit/SimpleTransformerContext
       317: dup
       318: invokedynamic #237,  0            // InvokeDynamic #20:accept:()Ljava/util/function/Consumer;
       323: iconst_1
       324: iconst_0
       325: iconst_0
       326: invokespecial #90                 // Method dev/architectury/transformer/transformers/base/edit/SimpleTransformerContext."<init>":(Ljava/util/function/Consumer;ZZZ)V
       329: getstatic     #62                 // Field classpathProvider:Ldev/architectury/transformer/transformers/classpath/ReadClasspathProvider;
       332: aload_1
       333: invokevirtual #38                 // Method dev/architectury/transformer/TransformerRuntime$PathWithTransformersEntry.getPath:()Ljava/nio/file/Path;
       336: invokeinterface #80,  1           // InterfaceMethod java/nio/file/Path.toString:()Ljava/lang/String;
       341: new           #238                // class dev/architectury/transformer/RuntimeReloadFileAccess
       344: dup
       345: aload_2
       346: aload         8
       348: aload         7
       350: aload         5
       352: invokespecial #239                // Method dev/architectury/transformer/RuntimeReloadFileAccess."<init>":(Ljava/util/Map;Ljava/util/Map;Ljava/util/Map;Ldev/architectury/transformer/input/FileAccess;)V
       355: aload_1
       356: invokevirtual #76                 // Method dev/architectury/transformer/TransformerRuntime$PathWithTransformersEntry.getTransformers:()Ljava/util/List;
       359: invokestatic  #93                 // Method dev/architectury/transformer/Transform.runTransformers:(Ldev/architectury/transformer/transformers/base/edit/TransformerContext;Ldev/architectury/transformer/transformers/classpath/ReadClasspathProvider;Ljava/lang/String;Ldev/architectury/transformer/input/FileAccess;Ljava/util/List;)V
       362: aload_2
       363: aload         8
       365: invokeinterface #240,  2          // InterfaceMethod java/util/Map.putAll:(Ljava/util/Map;)V
       370: invokestatic  #148                // Method dev/architectury/transformer/agent/TransformerAgent.getInstrumentation:()Ljava/lang/instrument/Instrumentation;
       373: invokeinterface #180,  1          // InterfaceMethod java/lang/instrument/Instrumentation.isRedefineClassesSupported:()Z
       378: ifeq          481
       381: aload_3
       382: ifnull        467
       385: aload         7
       387: invokeinterface #141,  1          // InterfaceMethod java/util/Map.entrySet:()Ljava/util/Set;
       392: invokeinterface #241,  1          // InterfaceMethod java/util/Set.iterator:()Ljava/util/Iterator;
       397: astore        9
       399: aload         9
       401: invokeinterface #34,  1           // InterfaceMethod java/util/Iterator.hasNext:()Z
       406: ifeq          467
       409: aload         9
       411: invokeinterface #35,  1           // InterfaceMethod java/util/Iterator.next:()Ljava/lang/Object;
       416: checkcast     #107                // class java/util/Map$Entry
       419: astore        10
       421: aload_3
       422: new           #8                  // class java/lang/StringBuilder
       425: dup
       426: invokespecial #9                  // Method java/lang/StringBuilder."<init>":()V
       429: aload         10
       431: invokeinterface #108,  1          // InterfaceMethod java/util/Map$Entry.getKey:()Ljava/lang/Object;
       436: checkcast     #23                 // class java/lang/String
       439: invokevirtual #11                 // Method java/lang/StringBuilder.append:(Ljava/lang/String;)Ljava/lang/StringBuilder;
       442: ldc           #224                // String .class
       444: invokevirtual #11                 // Method java/lang/StringBuilder.append:(Ljava/lang/String;)Ljava/lang/StringBuilder;
       447: invokevirtual #15                 // Method java/lang/StringBuilder.toString:()Ljava/lang/String;
       450: aload         10
       452: invokeinterface #124,  1          // InterfaceMethod java/util/Map$Entry.getValue:()Ljava/lang/Object;
       457: checkcast     #242                // class "[B"
       460: invokevirtual #243                // Method dev/architectury/transformer/input/DirectoryFileAccess.modifyFile:(Ljava/lang/String;[B)[B
       463: pop
       464: goto          399
       467: aload_1
       468: invokevirtual #38                 // Method dev/architectury/transformer/TransformerRuntime$PathWithTransformersEntry.getPath:()Ljava/nio/file/Path;
       471: invokeinterface #80,  1           // InterfaceMethod java/nio/file/Path.toString:()Ljava/lang/String;
       476: aload         7
       478: invokestatic  #244                // Method redefineClasses:(Ljava/lang/String;Ljava/util/Map;)V
       481: aload         5
       483: ifnull        568
       486: aload         6
       488: ifnull        511
       491: aload         5
       493: invokevirtual #52                 // Method dev/architectury/transformer/input/OpenedFileAccess.close:()V
       496: goto          568
       499: astore        7
       501: aload         6
       503: aload         7
       505: invokevirtual #54                 // Method java/lang/Throwable.addSuppressed:(Ljava/lang/Throwable;)V
       508: goto          568
       511: aload         5
       513: invokevirtual #52                 // Method dev/architectury/transformer/input/OpenedFileAccess.close:()V
       516: goto          568
       519: astore        7
       521: aload         7
       523: astore        6
       525: aload         7
       527: athrow
       528: astore        12
       530: aload         5
       532: ifnull        565
       535: aload         6
       537: ifnull        560
       540: aload         5
       542: invokevirtual #52                 // Method dev/architectury/transformer/input/OpenedFileAccess.close:()V
       545: goto          565
       548: astore        13
       550: aload         6
       552: aload         13
       554: invokevirtual #54                 // Method java/lang/Throwable.addSuppressed:(Ljava/lang/Throwable;)V
       557: goto          565
       560: aload         5
       562: invokevirtual #52                 // Method dev/architectury/transformer/input/OpenedFileAccess.close:()V
       565: aload         12
       567: athrow
       568: goto          578
       571: astore        5
       573: aload         5
       575: invokevirtual #245                // Method java/lang/Exception.printStackTrace:()V
       578: return
      Exception table:
         from    to  target type
            62    67    70   Class java/lang/Throwable
            45    52    90   Class java/lang/Throwable
            45    52    99   any
           111   116   119   Class java/lang/Throwable
            90   101    99   any
           491   496   499   Class java/lang/Throwable
             9   481   519   Class java/lang/Throwable
             9   481   528   any
           540   545   548   Class java/lang/Throwable
           519   530   528   any
             0   568   571   Class java/lang/Exception

  private static void lambda$null$5(java.lang.String[]);
    Code:
         0: return

  private static void lambda$main$4(java.util.List, java.lang.String[]);
    Code:
         0: aload_0
         1: aload_1
         2: invokestatic  #18                 // Method java/util/Arrays.asList:([Ljava/lang/Object;)Ljava/util/List;
         5: invokeinterface #246,  2          // InterfaceMethod java/util/List.addAll:(Ljava/util/Collection;)Z
        10: pop
        11: new           #8                  // class java/lang/StringBuilder
        14: dup
        15: invokespecial #9                  // Method java/lang/StringBuilder."<init>":()V
        18: ldc           #247                // String Appended Launch Argument:
        20: invokevirtual #11                 // Method java/lang/StringBuilder.append:(Ljava/lang/String;)Ljava/lang/StringBuilder;
        23: aload_1
        24: invokestatic  #248                // Method java/util/Arrays.toString:([Ljava/lang/Object;)Ljava/lang/String;
        27: invokevirtual #11                 // Method java/lang/StringBuilder.append:(Ljava/lang/String;)Ljava/lang/StringBuilder;
        30: invokevirtual #15                 // Method java/lang/StringBuilder.toString:()Ljava/lang/String;
        33: invokestatic  #84                 // Method dev/architectury/transformer/util/Logger.debug:(Ljava/lang/String;)V
        36: return

  private static boolean lambda$main$3(java.util.List, java.nio.file.Path);
    Code:
         0: aload_1
         1: invokeinterface #94,  1           // InterfaceMethod java/nio/file/Path.toFile:()Ljava/io/File;
         6: invokevirtual #44                 // Method java/io/File.getAbsoluteFile:()Ljava/io/File;
         9: astore_2
        10: aload_0
        11: invokeinterface #33,  1           // InterfaceMethod java/util/List.iterator:()Ljava/util/Iterator;
        16: astore_3
        17: aload_3
        18: invokeinterface #34,  1           // InterfaceMethod java/util/Iterator.hasNext:()Z
        23: ifeq          57
        26: aload_3
        27: invokeinterface #35,  1           // InterfaceMethod java/util/Iterator.next:()Ljava/lang/Object;
        32: checkcast     #36                 // class dev/architectury/transformer/TransformerRuntime$PathWithTransformersEntry
        35: astore        4
        37: aload         4
        39: invokevirtual #43                 // Method dev/architectury/transformer/TransformerRuntime$PathWithTransformersEntry.toFile:()Ljava/io/File;
        42: invokevirtual #44                 // Method java/io/File.getAbsoluteFile:()Ljava/io/File;
        45: aload_2
        46: invokestatic  #211                // Method java/util/Objects.equals:(Ljava/lang/Object;Ljava/lang/Object;)Z
        49: ifeq          54
        52: iconst_0
        53: ireturn
        54: goto          17
        57: iconst_1
        58: ireturn

  private static void lambda$main$2(dev.architectury.transformer.TransformerRuntime$PathWithTransformersEntry, dev.architectury.transformer.input.MemoryFileAccess, dev.architectury.transformer.input.DirectoryFileAccess, java.lang.String);
    Code:
         0: aload_3
         1: invokestatic  #249                // Method dev/architectury/transformer/Transform.trimSlashes:(Ljava/lang/String;)Ljava/lang/String;
         4: astore        4
         6: getstatic     #176                // Field CLASSES_TO_TRANSFORM:Ljava/util/Map;
         9: aload         4
        11: new           #250                // class dev/architectury/transformer/TransformerRuntime$ToTransformData
        14: dup
        15: aload_0
        16: invokevirtual #76                 // Method dev/architectury/transformer/TransformerRuntime$PathWithTransformersEntry.getTransformers:()Ljava/util/List;
        19: aload_1
        20: aload_2
        21: invokespecial #251                // Method dev/architectury/transformer/TransformerRuntime$ToTransformData."<init>":(Ljava/util/List;Ldev/architectury/transformer/input/FileAccess;Ldev/architectury/transformer/input/FileAccess;)V
        24: invokeinterface #252,  3          // InterfaceMethod java/util/Map.put:(Ljava/lang/Object;Ljava/lang/Object;)Ljava/lang/Object;
        29: pop
        30: return

  private static void lambda$main$1(dev.architectury.transformer.TransformerRuntime$PathWithTransformersEntry, dev.architectury.transformer.input.MemoryFileAccess, dev.architectury.transformer.input.DirectoryFileAccess, java.lang.String);
    Code:
         0: aload_3
         1: invokestatic  #249                // Method dev/architectury/transformer/Transform.trimSlashes:(Ljava/lang/String;)Ljava/lang/String;
         4: astore        4
         6: getstatic     #176                // Field CLASSES_TO_TRANSFORM:Ljava/util/Map;
         9: aload         4
        11: new           #250                // class dev/architectury/transformer/TransformerRuntime$ToTransformData
        14: dup
        15: aload_0
        16: invokevirtual #76                 // Method dev/architectury/transformer/TransformerRuntime$PathWithTransformersEntry.getTransformers:()Ljava/util/List;
        19: aload_1
        20: aload_2
        21: invokespecial #251                // Method dev/architectury/transformer/TransformerRuntime$ToTransformData."<init>":(Ljava/util/List;Ldev/architectury/transformer/input/FileAccess;Ldev/architectury/transformer/input/FileAccess;)V
        24: invokeinterface #252,  3          // InterfaceMethod java/util/Map.put:(Ljava/lang/Object;Ljava/lang/Object;)Ljava/lang/Object;
        29: pop
        30: return

  private static dev.architectury.transformer.input.DirectoryFileAccess lambda$main$0(dev.architectury.transformer.TransformerRuntime$PathWithTransformersEntry, java.util.concurrent.atomic.AtomicInteger, java.nio.file.Path);
    Code:
         0: ldc           #253                // String architectury.transformer.location
         2: ldc           #254                // String user.dir
         4: invokestatic  #22                 // Method java/lang/System.getProperty:(Ljava/lang/String;)Ljava/lang/String;
         7: invokestatic  #5                  // Method java/lang/System.getProperty:(Ljava/lang/String;Ljava/lang/String;)Ljava/lang/String;
        10: iconst_0
        11: anewarray     #23                 // class java/lang/String
        14: invokestatic  #24                 // Method java/nio/file/Paths.get:(Ljava/lang/String;[Ljava/lang/String;)Ljava/nio/file/Path;
        17: new           #8                  // class java/lang/StringBuilder
        20: dup
        21: invokespecial #9                  // Method java/lang/StringBuilder."<init>":()V
        24: ldc           #255                // String .architectury-transformer/debug-
        26: invokevirtual #11                 // Method java/lang/StringBuilder.append:(Ljava/lang/String;)Ljava/lang/StringBuilder;
        29: aload_0
        30: invokevirtual #38                 // Method dev/architectury/transformer/TransformerRuntime$PathWithTransformersEntry.getPath:()Ljava/nio/file/Path;
        33: invokeinterface #235,  1          // InterfaceMethod java/nio/file/Path.getFileName:()Ljava/nio/file/Path;
        38: invokeinterface #80,  1           // InterfaceMethod java/nio/file/Path.toString:()Ljava/lang/String;
        43: invokevirtual #11                 // Method java/lang/StringBuilder.append:(Ljava/lang/String;)Ljava/lang/StringBuilder;
        46: ldc_w         #256                // String -
        49: invokevirtual #11                 // Method java/lang/StringBuilder.append:(Ljava/lang/String;)Ljava/lang/StringBuilder;
        52: aload_1
        53: invokevirtual #257                // Method java/util/concurrent/atomic/AtomicInteger.incrementAndGet:()I
        56: invokevirtual #78                 // Method java/lang/StringBuilder.append:(I)Ljava/lang/StringBuilder;
        59: invokevirtual #15                 // Method java/lang/StringBuilder.toString:()Ljava/lang/String;
        62: invokeinterface #258,  2          // InterfaceMethod java/nio/file/Path.resolve:(Ljava/lang/String;)Ljava/nio/file/Path;
        67: astore_3
        68: aload_3
        69: iconst_0
        70: anewarray     #68                 // class java/nio/file/attribute/FileAttribute
        73: invokestatic  #259                // Method java/nio/file/Files.createDirectories:(Ljava/nio/file/Path;[Ljava/nio/file/attribute/FileAttribute;)Ljava/nio/file/Path;
        76: pop
        77: aload_3
        78: invokestatic  #260                // Method dev/architectury/transformer/input/DirectoryFileAccess.of:(Ljava/nio/file/Path;)Ldev/architectury/transformer/input/DirectoryFileAccess;
        81: areturn
        82: astore_3
        83: new           #262                // class java/io/UncheckedIOException
        86: dup
        87: aload_3
        88: invokespecial #263                // Method java/io/UncheckedIOException."<init>":(Ljava/io/IOException;)V
        91: athrow
      Exception table:
         from    to  target type
             0    81    82   Class java/io/IOException

  static {};
    Code:
         0: new           #126                // class java/util/HashSet
         3: dup
         4: invokespecial #127                // Method java/util/HashSet."<init>":()V
         7: putstatic     #42                 // Field TRANSFORM_FILES:Ljava/util/Set;
        10: new           #64                 // class java/util/HashMap
        13: dup
        14: invokespecial #65                 // Method java/util/HashMap."<init>":()V
        17: putstatic     #176                // Field CLASSES_TO_TRANSFORM:Ljava/util/Map;
        20: return
}
